{
  "type": "FeatureCollection",
  "features": [
    {
      "type": "Feature",
      "geometry": {
        "type": "Point",
        "coordinates": [
          -3.901878,
          40.327945
        ]
      },
      "properties": {
        "Identificador": 1,
        "Nombre": "Laguna del Soto",
        "Municipio": "Móstoles",
        "Tipo": "Laguna",
        "Superficie_m2": null,
        "Profundidad": null,
        "Comentarios": null,
        "fecha_actualizacion": "2025-11-21T00:00:00"
      }
    }
  ]
}
